rankify/__init__.py
rankify/__main__.py
rankify/__version__.py
rankify/agent/__init__.py
rankify/cli/__init__.py
rankify/cli/cli.py
rankify/dataset/__init__.py
rankify/dataset/dataset.py
rankify/generator/generator.py
rankify/generator/prompt_generator.py
rankify/generator/prompt_template.py
rankify/generator/models/base_rag_model.py
rankify/generator/models/fid_model.py
rankify/generator/models/huggingface_model.py
rankify/generator/models/litellm_model.py
rankify/generator/models/model_factory.py
rankify/generator/models/openai_model.py
rankify/generator/models/vllm_model.py
rankify/generator/rag_methods/base_rag_method.py
rankify/generator/rag_methods/basic_rag.py
rankify/generator/rag_methods/chain_of_thought_rag.py
rankify/generator/rag_methods/fid_rag_method.py
rankify/generator/rag_methods/in_context_ralm_rag.py
rankify/generator/rag_methods/react_rag.py
rankify/generator/rag_methods/self_consistency_rag.py
rankify/generator/rag_methods/zero_shot.py
rankify/indexing/__init__.py
rankify/indexing/ance_indexer.py
rankify/indexing/base_indexer.py
rankify/indexing/bge_indexer.py
rankify/indexing/colbert_indexer.py
rankify/indexing/contriever_indexer.py
rankify/indexing/dpr_indexer.py
rankify/indexing/format_converters.py
rankify/indexing/lucene_indexer.py
rankify/metrics/__init__.py
rankify/metrics/base_metrics.py
rankify/metrics/generator_metrics.py
rankify/metrics/metrics.py
rankify/metrics/ragas_bridge.py
rankify/metrics/retriever_metrics.py
rankify/models/__init__.py
rankify/models/apiranker.py
rankify/models/base.py
rankify/models/blender_reranker.py
rankify/models/colbert_ranker.py
rankify/models/echorank.py
rankify/models/first_reranker.py
rankify/models/flashrank.py
rankify/models/incontext_reranker.py
rankify/models/inranker.py
rankify/models/listt5.py
rankify/models/lit5_reranker.py
rankify/models/llm2vec_reranker.py
rankify/models/llm_layerwise_ranker.py
rankify/models/monobert.py
rankify/models/monot5.py
rankify/models/monot5_.py
rankify-0.1.4.dist-info/METADATA
rankify-0.1.4.dist-info/WHEEL
rankify-0.1.4.dist-info/entry_points.txt
rankify-0.1.4.dist-info/top_level.txt
rankify-0.1.4.dist-info/RECORD
