Metadata-Version: 2.4
Name: rankify
Version: 0.1.4
Summary: A Comprehensive Python Toolkit for Retrieval, Re-Ranking, and Retrieval-Augmented Generation
Author-email: Abdelrahman Abdallah <abdoelsayed2016@gmail.com>
Maintainer-email: Abdelrahman Abdallah <abdoelsayed2016@gmail.com>
Project-URL: Homepage, https://github.com/DataScienceUIBK/rankify
Project-URL: Documentation, http://rankify.readthedocs.io/
Project-URL: Issues, https://github.com/DataScienceUIBK/rankify/issues
Project-URL: Source Code, https://github.com/DataScienceUIBK/rankify
Project-URL: Hugging Face Dataset, https://huggingface.co/datasets/abdoelsayed/reranking-datasets
Project-URL: PyPI, https://pypi.org/project/rankify/
Keywords: retrieval,re-ranking,RAG,nlp,search
Classifier: Programming Language :: Python :: 3
Classifier: Programming Language :: Python :: 3.10
Classifier: Programming Language :: Python :: 3.11
Classifier: Programming Language :: Python :: 3.12
Classifier: Programming Language :: Python :: 3 :: Only
Requires-Python: >=3.10
Requires-Dist: pandas==2.2.3
Requires-Dist: prettytable==3.11.0
Requires-Dist: tqdm==4.66.5
Requires-Dist: requests==2.32.3
Requires-Dist: httpx==0.27.2
Requires-Dist: dacite==1.8.1
Requires-Dist: ftfy==6.3.1
Requires-Dist: transformers==4.45.2
Requires-Dist: datasets==3.2.0
Requires-Dist: sentence_transformers==3.3.0
Requires-Dist: onnxruntime==1.19.2
Requires-Dist: sentencepiece==0.2.0
Provides-Extra: reranking
Requires-Dist: vllm==0.7.0; extra == "reranking"
Requires-Dist: ninja==1.11.1.3; extra == "reranking"
Requires-Dist: llm-blender==0.0.2; extra == "reranking"
Requires-Dist: peft==0.14.0; extra == "reranking"
Requires-Dist: llama-cpp-python==0.2.76; extra == "reranking"
Requires-Dist: together==1.3.3; extra == "reranking"
Requires-Dist: cohere==5.14.0; extra == "reranking"
Provides-Extra: retriever
Requires-Dist: pyserini==0.43.0; extra == "retriever"
Requires-Dist: faiss-cpu==1.9.0.post1; extra == "retriever"
Requires-Dist: h5py==3.12.1; extra == "retriever"
Requires-Dist: omegaconf==2.3.0; extra == "retriever"
Requires-Dist: py7zr==0.22.0; extra == "retriever"
Requires-Dist: ujson==5.10.0; extra == "retriever"
Requires-Dist: gitpython==3.1.44; extra == "retriever"
Requires-Dist: langchain>=0.3.19; extra == "retriever"
Requires-Dist: fasttext-wheel>=0.9.2; extra == "retriever"
Requires-Dist: wikipedia-api>=0.8.1; extra == "retriever"
Requires-Dist: pillow>=10.4.0; extra == "retriever"
Requires-Dist: loguru==0.7.3; extra == "retriever"
Requires-Dist: beautifulsoup4; extra == "retriever"
Requires-Dist: html2text==2025.4.15; extra == "retriever"
Requires-Dist: Crawl4AI>=0.6.3; extra == "retriever"
Provides-Extra: rag
Requires-Dist: openai==1.68.2; extra == "rag"
Requires-Dist: litellm>=1.61.20; extra == "rag"
Requires-Dist: anthropic==0.37.1; extra == "rag"
Provides-Extra: all
Requires-Dist: rankify[reranking]; extra == "all"
Requires-Dist: rankify[retriever]; extra == "all"
Requires-Dist: rankify[rag]; extra == "all"
Provides-Extra: dev
Requires-Dist: build>=0.10.0; extra == "dev"
Requires-Dist: twine>=4.0.0; extra == "dev"
Requires-Dist: pytest>=7.0.0; extra == "dev"
Requires-Dist: ruff>=0.1.0; extra == "dev"
Requires-Dist: isort>=5.0.0; extra == "dev"
Requires-Dist: ipython>=8.0.0; extra == "dev"
